ms_agent/__init__.py
ms_agent/version.py
ms_agent/agent/__init__.py
ms_agent/agent/agent.yaml
ms_agent/agent/agent_skill.py
ms_agent/agent/base.py
ms_agent/agent/code_agent.py
ms_agent/agent/llm_agent.py
ms_agent/agent/loader.py
ms_agent/agent/runtime.py
ms_agent/app/__init__.py
ms_agent/app/doc_research.py
ms_agent/app/fin_research.py
ms_agent/callbacks/__init__.py
ms_agent/callbacks/base.py
ms_agent/callbacks/input_callback.py
ms_agent/callbacks/utils.py
ms_agent/cli/__init__.py
ms_agent/cli/app.py
ms_agent/cli/base.py
ms_agent/cli/cli.py
ms_agent/cli/run.py
ms_agent/config/__init__.py
ms_agent/config/config.py
ms_agent/config/env.py
ms_agent/llm/__init__.py
ms_agent/llm/anthropic_llm.py
ms_agent/llm/claude.py
ms_agent/llm/dashscope_llm.py
ms_agent/llm/deepseek_llm.py
ms_agent/llm/llm.py
ms_agent/llm/model_mapping.py
ms_agent/llm/modelscope_llm.py
ms_agent/llm/openai.py
ms_agent/llm/openai_llm.py
ms_agent/llm/utils.py
ms_agent/memory/__init__.py
ms_agent/memory/base.py
ms_agent/memory/default_memory.py
ms_agent/memory/diversity.py
ms_agent/memory/memory_manager.py
ms_agent/memory/utils.py
ms_agent/memory/condenser/__init__.py
ms_agent/memory/condenser/code_condenser.py
ms_agent/memory/condenser/refine_condenser.py
ms_agent/rag/__init__.py
ms_agent/rag/base.py
ms_agent/rag/extraction.py
ms_agent/rag/extraction_manager.py
ms_agent/rag/llama_index_rag.py
ms_agent/rag/schema.py
ms_agent/rag/utils.py
ms_agent/sandbox/__init__.py
ms_agent/sandbox/sandbox.py
ms_agent/skill/__init__.py
ms_agent/skill/loader.py
ms_agent/skill/prompts.py
ms_agent/skill/retrieve.py
ms_agent/skill/schema.py
ms_agent/skill/skill_utils.py
ms_agent/skill/spec.py
ms_agent/tools/__init__.py
ms_agent/tools/base.py
ms_agent/tools/filesystem_tool.py
ms_agent/tools/mcp_client.py
ms_agent/tools/search_engine.py
ms_agent/tools/split_task.py
ms_agent/tools/tool_manager.py
ms_agent/tools/audio_generator/__init__.py
ms_agent/tools/audio_generator/audio_gen.py
ms_agent/tools/audio_generator/edge_tts.py
ms_agent-1.5.2.dist-info/licenses/LICENSE
ms_agent-1.5.2.dist-info/METADATA
ms_agent-1.5.2.dist-info/WHEEL
ms_agent-1.5.2.dist-info/entry_points.txt
ms_agent-1.5.2.dist-info/top_level.txt
ms_agent-1.5.2.dist-info/RECORD
