Metadata-Version: 2.4
Name: ms-agent
Version: 1.5.2
Summary: MS-Agent: Lightweight Framework for Empowering Agents with Autonomous Exploration
Home-page: https://github.com/modelscope/ms-agent
Author: The ModelScope teams
Author-email: contact@modelscope.cn
License: Apache License 2.0
Keywords: python,agent,LLM
Classifier: Development Status :: 4 - Beta
Classifier: License :: OSI Approved :: Apache Software License
Classifier: Operating System :: OS Independent
Classifier: Programming Language :: Python :: 3
Classifier: Programming Language :: Python :: 3.8
Classifier: Programming Language :: Python :: 3.9
Classifier: Programming Language :: Python :: 3.10
Classifier: Programming Language :: Python :: 3.11
Classifier: Programming Language :: Python :: 3.12
License-File: LICENSE
Requires-Dist: dotenv
Requires-Dist: json5
Requires-Dist: markdown
Requires-Dist: mcp
Requires-Dist: modelscope
Requires-Dist: numpy
Requires-Dist: omegaconf
Requires-Dist: openai
Requires-Dist: pillow
Provides-Extra: research
Requires-Dist: arxiv; extra == "research"
Requires-Dist: docling<=2.38.1; extra == "research"
Requires-Dist: docling-core<=2.38.2; extra == "research"
Requires-Dist: exa-py; extra == "research"
Requires-Dist: google-search-results; extra == "research"
Requires-Dist: gradio>=5.0.0; extra == "research"
Requires-Dist: json5; extra == "research"
Requires-Dist: markdown; extra == "research"
Requires-Dist: mcp; extra == "research"
Requires-Dist: modelscope; extra == "research"
Requires-Dist: openai; extra == "research"
Requires-Dist: Pillow; extra == "research"
Requires-Dist: python-dotenv; extra == "research"
Requires-Dist: requests; extra == "research"
Provides-Extra: code
Requires-Dist: llama-index-core; extra == "code"
Requires-Dist: llama-index-embeddings-huggingface; extra == "code"
Requires-Dist: mem0ai; extra == "code"
Provides-Extra: all
Requires-Dist: dotenv; extra == "all"
Requires-Dist: json5; extra == "all"
Requires-Dist: markdown; extra == "all"
Requires-Dist: mcp; extra == "all"
Requires-Dist: modelscope; extra == "all"
Requires-Dist: numpy; extra == "all"
Requires-Dist: omegaconf; extra == "all"
Requires-Dist: openai; extra == "all"
Requires-Dist: pillow; extra == "all"
Requires-Dist: arxiv; extra == "all"
Requires-Dist: docling<=2.38.1; extra == "all"
Requires-Dist: docling-core<=2.38.2; extra == "all"
Requires-Dist: exa-py; extra == "all"
Requires-Dist: google-search-results; extra == "all"
Requires-Dist: gradio>=5.0.0; extra == "all"
Requires-Dist: json5; extra == "all"
Requires-Dist: markdown; extra == "all"
Requires-Dist: mcp; extra == "all"
Requires-Dist: modelscope; extra == "all"
Requires-Dist: openai; extra == "all"
Requires-Dist: Pillow; extra == "all"
Requires-Dist: python-dotenv; extra == "all"
Requires-Dist: requests; extra == "all"
Requires-Dist: llama-index-core; extra == "all"
Requires-Dist: llama-index-embeddings-huggingface; extra == "all"
Requires-Dist: mem0ai; extra == "all"
Dynamic: author
Dynamic: author-email
Dynamic: classifier
Dynamic: description
Dynamic: description-content-type
Dynamic: home-page
Dynamic: keywords
Dynamic: license
Dynamic: license-file
Dynamic: provides-extra
Dynamic: requires-dist
Dynamic: summary
